Moore_Machine/Moore_M.v
module Sequence_10110(
 input clk , rst , in ,
 output reg out 
);
    localparam s_0 = 3'b000;
    localparam s_1 = 3'b001;
    localparam s_2 = 3'b010;
    localparam s_3 = 3'b011;
    localparam s_4 = 3'b101;
    localparam s_5 = 3'b100;

    reg [2:0] c_s , n_s ;
  
    always @(posedge clk or negedge rst) begin
        if (!rst) c_s <= s_0 ;
        else c_s <= n_s ;
    end
        
  
  always @(*) begin
    case(c_s)
      s_0 : begin 
         n_s = in ? s_1 : s_0 ;
         out = 1'b0;
         end
      s_1 : begin
         n_s = in ? s_1 : s_2 ;
         out = 1'b0;
         end
      s_2 : begin
         n_s = in ? s_3 : s_0 ;
         out = 1'b0;
         end
      s_3 : begin
         n_s = in ? s_4 : s_2 ;
         out = 1'b0;
         end
      s_4 : begin
         n_s = in ? s_1 : s_5 ;
         out = 1'b0;
         end
      s_5 : begin
         n_s = in ? s_4 : s_0 ;
         out = 1'b1 ;
         end
     default : begin 
         n_s = s_0 ;
         out = 1'b0 ;
         end
    endcase
  end
    
endmodule

Moore_Machine/Moore_M_tb.v
`timescale 1ns/1ns
`include "Moore_M.v"

module sequence_tb;
    initial begin
        $dumpfile("Moore_M_tb.vcd");
        $dumpvars(0,sequence_tb); 
    end

    reg clk_tb , rst_tb , in_tb;
    wire out_tb;

    Sequence_10110 uut(
      .clk(clk_tb),
      .rst(rst_tb),
      .in(in_tb),
      .out(out_tb)
    );

    initial begin
      $monitor (clk_tb , rst_tb , in_tb ,out_tb);
    end

    initial clk_tb = 1;
    always #10 clk_tb = ~clk_tb;

   initial begin
    rst_tb = 1;
     in_tb = 0 ;
     #20
     in_tb = 0 ; 
     #20
     in_tb = 1 ;
     #20
     in_tb = 0 ;
     #20
     in_tb = 1 ;
     #20
     in_tb = 1 ;
     #15
     in_tb = 0 ;
     #15
     in_tb = 1 ;
     #20
     in_tb = 1 ;
     #20
     in_tb = 0 ; 
     #1000
    $finish;
    end
endmodule

Moore_Machine/Moore_M_tb.vcd
$date
	Thu Oct  5 06:39:58 2023
$end
$version
	Icarus Verilog
$end
$timescale
	1ns
$end
$scope module sequence_tb $end
$var wire 1 ! out_tb $end
$var reg 1 " clk_tb $end
$var reg 1 # in_tb $end
$var reg 1 $ rst_tb $end
$scope module uut $end
$var wire 1 " clk $end
$var wire 1 # in $end
$var wire 1 $ rst $end
$var reg 3 % c_s [2:0] $end
$var reg 3 & n_s [2:0] $end
$var reg 1 ! out $end
$upscope $end
$upscope $end
$enddefinitions $end
#0
$dumpvars
b0 &
bx %
1$
0#
1"
0!
$end
#10
0"
#20
b0 %
1"
#30
0"
#40
b1 %
b1 &
1"
1#
#50
0"
#60
b10 %
b0 &
1"
0#
#70
0"
#80
b11 %
b101 &
1"
1#
#90
0"
#100
b1 &
b101 %
1"
#110
0"
#115
b100 &
0#
#120
1!
b0 &
b100 %
1"
#130
b101 &
0"
1#
#140
0!
b1 &
b101 %
1"
#150
0"
#160
b1 %
1"
#170
b10 &
0"
0#
#180
b0 &
b10 %
1"
#190
0"
#200
b0 %
1"
