Meelay_Machine/Meelay_Machine.v
module Sequence_1010(
 input clk , rst , in ,
 output reg out 
);
    localparam s_0 = 2'b00;
    localparam s_1 = 2'b01;
    localparam s_2 = 2'b10;
    localparam s_3 = 2'b11;

    reg [1:0] c_s , n_s ;
  
    always @(posedge clk or negedge rst) begin
        if (!rst) c_s <= s_0 ;
        else c_s <= n_s ;
    end
        
  
  always @(*) begin
    case(c_s)
      s_0 : begin 
         n_s = in ? s_1 : s_0 ;
         out = 1'b0;
         end
      s_1 : begin
         n_s = in ? s_1 : s_2 ;
         out = 1'b0;
         end
      s_2 : begin
         n_s = in ? s_3 : s_0 ;
         out = 1'b0;
         end
      s_3 : begin
         n_s = in ? s_1 : s_2 ;
         out = in ? 1'b0 : 1'b1 ;
         end
     default : begin 
         n_s = s_0 ;
         out = 1'b0 ;
         end
    endcase
  end
    
endmodule

Meelay_Machine/Meelay_Machine_tb.v
`timescale 1ns/1ns
`include "Meelay_Machine.v"

module sequenc_tb;
    initial begin
        $dumpfile("Meelay_Machine_tb.vcd");
        $dumpvars(0,sequenc_tb); 
    end

    reg clk_tb , rst_tb , in_tb;
    wire out_tb;

    Sequence_1010 uut(
      .clk(clk_tb),
      .rst(rst_tb),
      .in(in_tb),
      .out(out_tb)
    );

    initial begin
      $monitor (clk_tb , rst_tb , in_tb ,out_tb);
    end

    initial clk_tb = 1;
    always #10 clk_tb = ~clk_tb;

   initial begin
    rst_tb = 1;
     in_tb = 1 ;
     #20
     in_tb = 0 ; 
     #20
     in_tb = 1 ;
     #20
     in_tb = 0 ;
     #20
     in_tb = 0 ;
     #20
     in_tb = 0 ;
     #20
     in_tb = 1 ;
     #20
     in_tb = 0 ;
     #20
     in_tb = 1 ;
     #18
     in_tb = 0 ; 
     #1000
    $finish;
    end  
endmodule

Meelay_Machine/Meelay_Machine_tb.vcd
$date
	Tue Oct 10 00:31:14 2023
$end
$version
	Icarus Verilog
$end
$timescale
	1ns
$end
$scope module sequenc_tb $end
$var wire 1 ! out_tb $end
$var reg 1 " clk_tb $end
$var reg 1 # in_tb $end
$var reg 1 $ rst_tb $end
$scope module uut $end
$var wire 1 " clk $end
$var wire 1 # in $end
$var wire 1 $ rst $end
$var reg 2 % c_s [1:0] $end
$var reg 2 & n_s [1:0] $end
$var reg 1 ! out $end
$upscope $end
$upscope $end
$enddefinitions $end
#0
$dumpvars
b0 &
bx %
1$
1#
1"
0!
$end
#10
0"
#20
b0 %
1"
0#
#30
0"
#40
b1 %
b1 &
1"
1#
#50
0"
#60
b10 %
b0 &
1"
0#
#70
0"
#80
b0 %
1"
#90
0"
#100
1"
#110
0"
#120
b1 %
b1 &
1"
1#
#130
0"
#140
b10 %
b0 &
1"
0#
#150
0"
#160
b11 %
b1 &
1"
1#
#170
0"
#178
1!
b10 &
0#
#180
0!
b0 &
b10 %
1"
#190
0"
#200
b0 %
1"
