Traffic_system/traffic_system.v
module traffic_system(
 input  clk , rst , in ,
 output reg [1:0] M_H , L_R
);
    localparam s_0 = 2'b00;
    localparam s_1 = 2'b01;
    localparam s_2 = 2'b10;
    localparam s_3 = 2'b11;

    reg [1:0] c_s , n_s ;
  
    always @(posedge clk or negedge rst) begin
        if (!rst) c_s <= s_0 ;
        else c_s <= n_s ;
    end
        
  
  always @(*) begin

    case(c_s)
      s_0 : begin 
         n_s = in ? s_1 : s_0 ;
          M_H = 2'b11;
          L_R = 2'b00;
         end
      s_1 : begin
         n_s = in ? s_2 : s_0 ;
         M_H = 2'b00;
         L_R = 2'b10;
         end
      s_2 : begin
         n_s = in ? s_2 : s_3 ;
         M_H = 2'b00;
         L_R = 2'b11;
         end
      s_3 : begin
         n_s = in ? s_2 : s_0 ;
         M_H = 2'b10;
         L_R = 2'b00;
         end
     default : begin  // 
         n_s = s_0 ;
         M_H = 2'b01;
         L_R = 2'b01; 
         end
    endcase
  end
    
endmodule

Traffic_system/traffic_system_tb.v
`timescale 1ns/1ns
`include "traffic_system.v"

module traffic_system_tb;
    initial begin
        $dumpfile("traffic_system_tb.vcd");
        $dumpvars(0,traffic_system_tb); 
    end

    reg clk_tb , rst_tb , in_tb;
    wire [1:0] M_H_tb , L_R_tb;

 traffic_system uut(
      .clk(clk_tb),
      .rst(rst_tb),
      .in(in_tb),
      .M_H(M_H_tb),
      .L_R(L_R_tb)
    );

    initial begin
      $monitor (clk_tb , rst_tb , in_tb , M_H_tb , L_R_tb);
    end

    initial clk_tb = 1;
    always #10 clk_tb = ~clk_tb;
    initial begin
       rst_tb = 0;
    #10
     rst_tb = 1;
     end

   initial begin
     in_tb = 0 ;
     #20
     in_tb = 0 ; 
     #20
     in_tb = 1 ;
     #20
     in_tb = 1 ;
     #20
     in_tb = 0 ;
     #20
     in_tb = 0 ;
     #20
     in_tb = 1 ;
     #20
     in_tb = 0 ;
     #20
     in_tb = 1 ;
     #18
     in_tb = 0 ; 
     #1000
    $finish;
    end
endmodule

Traffic_system/traffic_system_tb.vcd
$date
	Thu Oct  5 17:21:59 2023
$end
$version
	Icarus Verilog
$end
$timescale
	1ns
$end
$scope module traffic_system_tb $end
$var wire 2 ! M_H_tb [1:0] $end
$var wire 2 " L_R_tb [1:0] $end
$var reg 1 # clk_tb $end
$var reg 1 $ in_tb $end
$var reg 1 % rst_tb $end
$scope module uut $end
$var wire 1 # clk $end
$var wire 1 $ in $end
$var wire 1 % rst $end
$var reg 2 & L_R [1:0] $end
$var reg 2 ' M_H [1:0] $end
$var reg 2 ( c_s [1:0] $end
$var reg 2 ) n_s [1:0] $end
$upscope $end
$upscope $end
$enddefinitions $end
#0
$dumpvars
b0 )
b0 (
b11 '
b0 &
0%
0$
1#
b0 "
b11 !
$end
#10
1%
0#
#20
1#
#30
0#
#40
b10 "
b10 &
b0 !
b0 '
b1 (
b10 )
1#
1$
#50
0#
#60
b11 "
b11 &
b10 (
1#
#70
0#
#80
b0 "
b0 &
b10 !
b10 '
b11 (
b0 )
1#
0$
#90
0#
#100
b11 !
b11 '
b0 (
1#
#110
0#
#120
b10 "
b10 &
b0 !
b0 '
b1 (
b10 )
1#
1$
#130
0#
#140
b0 "
b0 &
b11 !
b11 '
b0 (
b0 )
1#
0$
#150
0#
#160
b10 "
b10 &
b0 !
b0 '
b1 (
b10 )
1#
1$
#170
0#
#178
b0 )
0$
#180
b0 "
b0 &
b11 !
b11 '
b0 (
1#
