Task_1_counter/task_1_counter.v
module task_1_counter(
 input  clk , rst , load , enab , 
 input  [3:0] cnt_in ,
 output reg  [3:0] cnt_out
);
   always@(posedge clk) 
  begin
    if(rst)    //Set Counter to Zero
      cnt_out <= 4'b0000;
    else if(load)    //load the counter with data value
      cnt_out <= cnt_in;
    else if(enab)        //count
      cnt_out <= cnt_out + 1;
  end   
endmodule

Task_1_counter/task_1_counter_tb.v
`timescale 1ns/1ns
`include "task_1_counter.v"

module task_1_counter_tb;
    initial begin
        $dumpfile("task_1_counter_tb.vcd");
        $dumpvars(0,task_1_counter_tb); 
    end

    reg clk_tb , rst_tb ,enab_tb , load_tb;
    reg [3:0] cnt_in_tb;
    wire [3:0] cnt_out_tb;

 task_1_counter uut(
      .clk(clk_tb),
      .rst(rst_tb),
      .load(load_tb),
      .enab(enab_tb),
      .cnt_in(cnt_in_tb),
      .cnt_out(cnt_out_tb)
    );

initial begin 
    $monitor("time=%0d,reset=%b,load=%b,enable=%b,cnt_in=%d,cnt_out=%d",
    $time,rst_tb,load_tb,enab_tb,cnt_in_tb,cnt_out_tb);
    end

    initial 
    clk_tb = 1'b1;
    always #5 clk_tb = ~clk_tb;
    

    initial begin
     rst_tb = 1;
    #5
     rst_tb = 0;
     #50
     rst_tb = 1;
      #10
     rst_tb = 0;
     end

  initial begin #18 load_tb = 1'b1; #5 load_tb = 1'b0; #5 load_tb = 1'b1;end
  initial begin #5 enab_tb = 1'b1; #27 enab_tb = 1'b0;end
  initial begin cnt_in_tb = 4'b1000; #15 cnt_in_tb = 4'b1101; #25 cnt_in_tb = 4'b1111;
    #1000
    $finish;
    end
endmodule

Task_1_counter/task_1_counter_tb.vcd
$date
	Thu Oct  5 18:45:02 2023
$end
$version
	Icarus Verilog
$end
$timescale
	1ns
$end
$scope module task_1_counter_tb $end
$var wire 4 ! cnt_out_tb [3:0] $end
$var reg 1 " clk_tb $end
$var reg 4 # cnt_in_tb [3:0] $end
$var reg 1 $ enab_tb $end
$var reg 1 % load_tb $end
$var reg 1 & rst_tb $end
$scope module uut $end
$var wire 1 " clk $end
$var wire 4 ' cnt_in [3:0] $end
$var wire 1 $ enab $end
$var wire 1 % load $end
$var wire 1 & rst $end
$var reg 4 ( cnt_out [3:0] $end
$upscope $end
$upscope $end
$enddefinitions $end
#0
$dumpvars
b0 (
b1000 '
1&
x%
x$
b1000 #
1"
b0 !
$end
#5
1$
0&
0"
#10
b1 !
b1 (
1"
#15
0"
b1101 #
b1101 '
#18
1%
#20
b1101 !
b1101 (
1"
#23
0%
#25
0"
#28
1%
#30
1"
#32
0$
#35
0"
#40
b1111 !
b1111 (
1"
b1111 #
b1111 '
#45
0"
#50
1"
#55
0"
1&
#60
b0 !
b0 (
1"
#65
0"
0&
#70
b1111 !
b1111 (
1"
